[1,["02v6bYvlFGpKEhOSqvkPxI@6c48a"],["_textureSource"],["cc.SpriteFrame"],0,[{"name":"Common_BG4_2x","rect":{"x":0,"y":0,"width":960,"height":641},"offset":{"x":-32,"y":191.5},"originalSize":{"width":1024,"height":1024},"rotated":false,"capInsets":[0,0,0,0],"vertices":{"rawPosition":[-480,-320.5,0,480,-320.5,0,-480,320.5,0,480,320.5,0],"indexes":[0,1,2,2,1,3],"uv":[0,1024,960,1024,0,383,960,383],"nuv":[0,0.3740234375,0.9375,0.3740234375,0,1,0.9375,1],"minPos":{"x":-480,"y":-320.5,"z":0},"maxPos":{"x":480,"y":320.5,"z":0}},"packable":true,"pixelsToUnit":100,"pivot":{"x":0.5,"y":0.5},"meshType":0}],[0],0,[0],[0],[0]]
